{
  "parent": "minecraft:recipes/root",
  "rewards": {
    "recipes": [
      "resourceslimes:uncut_citrine_from_blasting_raw_citrine"
    ]
  },
  "criteria": {
    "has_raw_citrine": {
      "trigger": "minecraft:inventory_changed",
      "conditions": {
        "items": [
          {
            "items": [
              "resourceslimes:raw_citrine"
            ]
          }
        ]
      }
    },
    "has_the_recipe": {
      "trigger": "minecraft:recipe_unlocked",
      "conditions": {
        "recipe": "resourceslimes:uncut_citrine_from_blasting_raw_citrine"
      }
    }
  },
  "requirements": [
    [
      "has_raw_citrine",
      "has_the_recipe"
    ]
  ]
}